[
  {
    "title": "High Quality Wholesale 100% Soft Fibre Polyester Men Tshirt Sublimation T Shirts Plain Custom Printing White Blank",
    "price": "$0.90",
    "company": "Suzhou Dreamcolor Textile Co., Ltd.",
    "moq": "Min. order: 10 pieces",
    "rating": "4.2",
    "image": "https://s.alicdn.com/@sc04/kf/H46929a0c6237421588cbb0aacd5dba110.jpg_300x300.jpg",
    "link": "https://www.alibaba.com/product-detail/High-Quality-Wholesale-100-Soft-Fibre_1600885886255.html?selectedCarrierCode=SEMI_MANAGED_STANDARD@@STANDARD"
  },
  {
    "title": "Contrasting color patchwork short sleeved T-shirt for summer new loose and fashionable casual half sleeved top",
    "price": "$3.50",
    "company": "Hebei Kang Sheng Yuan Sports Goods Co., Ltd.",
    "moq": "Min. order: 3 pieces",
    "rating": "4.3",
    "image": "https://s.alicdn.com/@sc04/kf/H7344b618af53437b8ad3e4c28df30935W.jpg_300x300.jpg",
    "link": "https://www.alibaba.com/product-detail/Contrasting-color-patchwork-short-sleeved-T_1601193223826.html?selectedCarrierCode=SEMI_MANAGED_STANDARD@@STANDARD"
  },
  {
    "title": "Premium Soft Cotton Hip Hop Blank Man's Oversized Heavyweight Tshirt 260 Gsm Drop Shoulder t Shirt",
    "price": "$5.85",
    "company": "Guangzhou Hengdong Sports Goods Co., Ltd.",
    "moq": "Min. order: 3 pieces",
    "rating": "4.6",
    "image": "https://s.alicdn.com/@sc04/kf/Hb04b3b3846a144c1be55a27efd1dc785M.jpg_300x300.jpg",
    "link": "https://www.alibaba.com/product-detail/Premium-Soft-Cotton-Hip-Hop-Blank_1600846041445.html?selectedCarrierCode=SEMI_MANAGED_STANDARD@@STANDARD"
  },
  {
    "title": "High Quality 290 Gsm Heavy weight Blank Man's Boxy T shirts oversized Cotton Box Fit shirts oversized box t shirt Solid Color",
    "price": "$5.90",
    "company": "Xiamen Maysun Industrial Co., Ltd.",
    "moq": "Min. order: 2 pieces",
    "rating": "4.7",
    "image": "https://s.alicdn.com/@sc04/kf/H5b1c8ffc50ba4731b63e0b5d2dc6dc16k.png_300x300.png",
    "link": "https://www.alibaba.com/product-detail/High-Quality-290-Gsm-Heavy-weight_1601270733144.html?selectedCarrierCode=SEMI_MANAGED_STANDARD@@STANDARD"
  },
  {
    "title": "CB04-76000 Free Inside Labels and Your Logo Cards Offer Cotton Custom T Shirt for Blank Tshirt Printing Basic",
    "price": "$4.99",
    "company": "Yiwu Custom Brand Commodity Co., Ltd.",
    "moq": "Min. order: 2 pieces",
    "rating": "4.8",
    "image": "https://s.alicdn.com/@sc04/kf/H1d456249e0904e9fb308976731475bcbJ.png_300x300.png",
    "link": "https://www.alibaba.com/product-detail/CB04-76000-Free-Inside-Labels-and_60238927820.html"
  },
  {
    "title": "good quality wholesale streetwear blank thick black 100% soft cotton t shirt 230 gsm oversized heavy t shirts for",
    "price": "$8.90",
    "company": "Shenzhen Yali Clothing Co., Ltd.",
    "moq": "Min. order: 100 pieces",
    "rating": "4.9",
    "image": "https://s.alicdn.com/@sc04/kf/H0361b3f31ef74c32b992e51271887d80e.jpg_300x300.jpg",
    "link": "https://www.alibaba.com/product-detail/good-quality-wholesale-streetwear-blank-thick_1600571288109.html"
  },
  {
    "title": "Mimixiong Factory Wholesale Custom Logo Green And White Fit Clothes Summer Short Sleeve Striped Pullover For Daily",
    "price": "$8.24",
    "company": "Fujian Nan' An Huangda Clothing Co., Ltd.",
    "moq": "Min. order: 2 pieces",
    "rating": "5.0",
    "image": "https://s.alicdn.com/@sc04/kf/Hcffcd3b86c3045cab6e0ed9ceb35fc36N.jpg_300x300.jpg",
    "link": "https://www.alibaba.com/product-detail/Mimixiong-Factory-Wholesale-Custom-Logo-Green_1601090934918.html?selectedCarrierCode=SEMI_MANAGED_STANDARD@@STANDARD"
  },
  {
    "title": "230g Washed Custom Plain Oversize Man's T-shirt High Quality 100% Cotton Washed Vintage t Shirt for Man",
    "price": "$6.88",
    "company": "Shenzhen Tehe Garment Accessories Co., Ltd.",
    "moq": "Min. order: 5 pieces",
    "rating": "4.9",
    "image": "https://s.alicdn.com/@sc04/kf/Hee31ddca94e44db7b48176770e125b55j.jpg_300x300.jpg",
    "link": "https://www.alibaba.com/product-detail/230g-Washed-Custom-Plain-Oversize-Man_1601060483028.html?selectedCarrierCode=SEMI_MANAGED_STANDARD@@STANDARD"
  },
  {
    "title": "High Quality 100% Cotton Blank Men's T-shirts Heavyweight Oversized Tshirt Printing Custom T Shirt",
    "price": "$5.99",
    "company": "Xiongxian Kaixin Cap Co., Ltd.",
    "moq": "Min. order: 25 pieces",
    "rating": "4.9",
    "image": "https://s.alicdn.com/@sc04/kf/H578085293bce4af190705e062c56c3d30.jpg_300x300.jpg",
    "link": "https://www.alibaba.com/product-detail/High-Quality-100-Cotton-Blank-Men_1600573411635.html?selectedCarrierCode=SEMI_MANAGED_STANDARD@@STANDARD"
  },
  {
    "title": "The Best Factory Price Long -sleeved Golf Ball T -shirt Is Breathless Wholesale Price Golf Shirt for Men",
    "price": "$5.20",
    "company": "Guangzhou Guanjun Clothing Technology Co., Ltd.",
    "moq": "Min. order: 30 pieces",
    "rating": "5.0",
    "image": "https://s.alicdn.com/@sc04/kf/H47a7878b5353446e969b95be740e03d2v.png_300x300.png",
    "link": "https://www.alibaba.com/product-detail/The-Best-Factory-Price-Long-sleeved_1600940206970.html?selectedCarrierCode=SEMI_MANAGED_STANDARD@@STANDARD"
  },
  {
    "title": "Wholesale 2024 new 260gsm heavyweight crewneck plain 100% cotton long sleeve t shirt with pocket unisex causal tshirts for",
    "price": "$8.12",
    "company": "Jiangxi Gift In Industrial Trade Co., Ltd.",
    "moq": "Min. order: 2 pieces",
    "rating": "4.8",
    "image": "https://s.alicdn.com/@sc04/kf/Hd2aea944d9414ba9824e559a0f5ec1a6R.jpg_300x300.jpg",
    "link": "https://www.alibaba.com/product-detail/Wholesale-2024-new-260gsm-heavyweight-crewneck_1601041303567.html"
  },
  {
    "title": "Shuliqi Plus Size Men's T-shirts Oversized Heavy Cotton,custom Oversized t Shirt,plus Size for 100% Cotton",
    "price": "$8.96",
    "company": "Guangzhou Shuliqi Garment Co., Ltd.",
    "moq": "Min. order: 5 pieces",
    "rating": "4.9",
    "image": "https://s.alicdn.com/@sc04/kf/Hdd0f5c6d5e52493080fec654fd4f3c9eP.jpg_300x300.jpg",
    "link": "https://www.alibaba.com/product-detail/Shuliqi-Plus-Size-Men-s-T_1600606714897.html"
  },
  {
    "title": "Blank Embroidery Print Man's Women Custom logo Plain Polyester Round Neck Dry-fit Long Sleeve Tee t Shirt for Me",
    "price": "$2.88",
    "company": "Yiwu Guanyu Trading Co., Ltd.",
    "moq": "Min. order: 5 pieces",
    "rating": "4.5",
    "image": "https://s.alicdn.com/@sc04/kf/H6efe19d616b847df8bb77ae2599503afc.jpg_300x300.jpg",
    "link": "https://www.alibaba.com/product-detail/Blank-Embroidery-Print-Man-s-Women_1600901511453.html?selectedCarrierCode=SEMI_MANAGED_STANDARD@@STANDARD"
  },
  {
    "title": "Men's short sleeve T-shirt men's trendy casual sports",
    "price": "$13.90",
    "company": "Guangzhou Healy Apparel Co., Ltd.",
    "moq": "Min. order: 2 pieces",
    "rating": "4.8",
    "image": "https://s.alicdn.com/@sc04/kf/H865381f18fab4867bbb05d3518d0d9f6p.jpg_300x300.jpg",
    "link": "https://www.alibaba.com/product-detail/Men-s-short-sleeve-T-shirt_1601075032888.html?selectedCarrierCode=SEMI_MANAGED_STANDARD@@STANDARD"
  },
  {
    "title": "Plus size unisex t.shirts men cotton plain men's t shirts 92 cotton 8 spandex solid comfortable t shirts",
    "price": "$15.00",
    "company": "Yangzhou Deniswear Apparel Co., Ltd.",
    "moq": "Min. order: 2 pieces",
    "rating": "4.1",
    "image": "https://s.alicdn.com/@sc04/kf/Hd72367772340433aa0b92de6b68983e1f.jpg_300x300.jpg",
    "link": "https://www.alibaba.com/product-detail/Plus-size-unisex-t-shirts-men_1601196348182.html?selectedCarrierCode=SEMI_MANAGED_STANDARD@@STANDARD"
  },
  {
    "title": "Hot Sale Soft Cotton Custom logo Blank Man's Oversized Heavyweight Tshirt 180 Gsm Drop Shoulder t Shirt",
    "price": "$3.50",
    "company": "Yiwu Qunshan Clothing Co., Ltd.",
    "moq": "Min. order: 2 pieces",
    "rating": "4.8",
    "image": "https://s.alicdn.com/@sc04/kf/H28bb3de317b34232bbe4541a68a3e406E.jpg_300x300.jpg",
    "link": "https://www.alibaba.com/product-detail/Hot-Sale-Soft-Cotton-Custom-logo_1601104027205.html?selectedCarrierCode=SEMI_MANAGED_STANDARD@@STANDARD"
  },
  {
    "title": "Streetwear Supplier Wholesale T-shirts For 360g 100% Cotton Long-sleeved Solid Color Hip-pop Unisex Loose",
    "price": "$15.90",
    "company": "Dongguan Rainbow Touches Garment Co., Ltd.",
    "moq": "Min. order: 2 pieces",
    "rating": "4.2",
    "image": "https://s.alicdn.com/@sc04/kf/H82753c49859c4c268bbb021ce71ebd27y.jpg_300x300.jpg",
    "link": "https://www.alibaba.com/product-detail/Streetwear-Supplier-Wholesale-T-shirts-For_1601020398629.html?selectedCarrierCode=SEMI_MANAGED_STANDARD@@STANDARD"
  },
  {
    "title": "Organic men t-shirt short sleeve t shirt custom tshirt for jersey clothes eco friendly summer high quality t-shirts",
    "price": "$7.00",
    "company": "Taian Lianchuang Textile Co., Ltd.",
    "moq": "Min. order: 2 pieces",
    "rating": "4.4",
    "image": "https://s.alicdn.com/@sc04/kf/H8f89bdfd7caa494eb9e93e283ed36e60P.jpg_300x300.jpg",
    "link": "https://www.alibaba.com/product-detail/Organic-men-t-shirt-short-sleeve_1601314147839.html?selectedCarrierCode=SEMI_MANAGED_STANDARD@@STANDARD"
  },
  {
    "title": "New Trend Fashion Mens T-shirts Casual Polo Neck High Quality Cotton Tshirt Polo T shirt",
    "price": "$50.00",
    "company": "Guangzhou Joyord Sportswear Co., Ltd.",
    "moq": "Min. order: 2 pieces",
    "rating": "4.9",
    "image": "https://s.alicdn.com/@sc04/kf/Hb50de8a289cf47e6bd006e82697a7249V.jpg_300x300.jpg",
    "link": "https://www.alibaba.com/product-detail/New-Trend-Fashion-Mens-T-shirts_1601033119514.html?selectedCarrierCode=SEMI_MANAGED_STANDARD@@STANDARD"
  },
  {
    "title": "Wholesale men's shirts blank t shirt high quality shirt for custom short sleeve 100% cotton",
    "price": "$8.60",
    "company": "Shandong Saier Garment Technology Co., Ltd.",
    "moq": "Min. order: 50 pieces",
    "rating": "4.8",
    "image": "https://s.alicdn.com/@sc04/kf/Hd3975fff6c8e441887e0338bce07160eW.jpg_300x300.jpg",
    "link": "https://www.alibaba.com/product-detail/Wholesale-men-s-shirts-blank-t_1601258095060.html"
  },
  {
    "title": "Street Style men's t shirt 210G Cotton causal Breathable crewneck short-sleeved heavyweight boxy cropped",
    "price": "$4.49",
    "company": "Henan Boders Industrial Limited Company",
    "moq": "Min. order: 2 pieces",
    "rating": "4.8",
    "image": "https://s.alicdn.com/@sc04/kf/He1bf0c242f154759961e45668e39044eJ.jpg_300x300.jpg",
    "link": "https://www.alibaba.com/product-detail/Street-Style-men-s-t-shirt_1601166205851.html?selectedCarrierCode=SEMI_MANAGED_STANDARD@@STANDARD"
  },
  {
    "title": "T shirts manufacturers Custom high quality men T Shirt Solid Color 100% Cotton Plus Size tshirt printing",
    "price": "$5.90",
    "company": "Beijing Qianbaidu Garment Co., Ltd.",
    "moq": "Min. order: 40 pieces",
    "rating": "4.8",
    "image": "https://s.alicdn.com/@sc04/kf/Hdea19897435b43b8aaae195c4ab280d42.jpg_300x300.jpg",
    "link": "https://www.alibaba.com/product-detail/T-shirts-manufacturers-Custom-high-quality_1600494518067.html?selectedCarrierCode=SEMI_MANAGED_STANDARD@@STANDARD"
  },
  {
    "title": "Men's Seamless Short-Sleeve T Shirt Mens Short Sleeve Sport Casual Quick Dry Breathable Running Fitted T Shirts Tops",
    "price": "$6.89",
    "company": "Wuxi Jihe Industrial Technology Co., Ltd.",
    "moq": "Min. order: 25 pieces",
    "rating": "4.6",
    "image": "https://s.alicdn.com/@sc04/kf/Hd966796d33fb4b5cb6668ccc57b1ce29J.jpg_300x300.jpg",
    "link": "https://www.alibaba.com/product-detail/Men-s-Seamless-Short-Sleeve-T_1601232785332.html?selectedCarrierCode=SEMI_MANAGED_STANDARD@@STANDARD"
  },
  {
    "title": "premium soft cotton hip hop streetwear blank man's oversized heavyweight base tshirt 230 gsm drop shoulder t shirt",
    "price": "$4.90",
    "company": "Guangxi Feibai Clothing Co., Ltd.",
    "moq": "Min. order: 50 pieces",
    "rating": "4.5",
    "image": "https://s.alicdn.com/@sc04/kf/H74f9d76c0c5e4433952bc33fac16baeaC.jpg_300x300.jpg",
    "link": "https://www.alibaba.com/product-detail/premium-soft-cotton-hip-hop-streetwear_1601190755707.html?selectedCarrierCode=SEMI_MANAGED_STANDARD@@STANDARD"
  },
  {
    "title": "Wholesale Cotton Unisex T-shirts Wash Printing Men's",
    "price": "$11.80",
    "company": "Dongguan Rainbow Spray Garment Co., Ltd.",
    "moq": "Min. order: 1 piece",
    "rating": "4.6",
    "image": "https://s.alicdn.com/@sc04/kf/Hcc947ec418304861a75d841b05671b8a1.jpg_300x300.jpg",
    "link": "https://www.alibaba.com/product-detail/Wholesale-Cotton-Unisex-T-shirts-Wash_1600491126905.html?selectedCarrierCode=SEMI_MANAGED_STANDARD@@STANDARD"
  },
  {
    "title": "Conyson Factory Price New Design Summer Man Fashion Loose Cotton Oversized T Shirt Fit Drop Shoulder Adult Soft",
    "price": "$4.50",
    "company": "Hangzhou Ciny Fashion Co., Ltd.",
    "moq": "Min. order: 5 pieces",
    "rating": "4.5",
    "image": "https://s.alicdn.com/@sc04/kf/Ad6a47da99112407396d82683c8d8c103G.jpg_300x300.jpg",
    "link": "https://www.alibaba.com/product-detail/Conyson-Factory-Price-New-Design-Summer_1601022377893.html"
  },
  {
    "title": "2024 Brand New Cotton Men's T-shirt Short-sleeve Short Sleeve Pure Color Custom Sublimation t shirt T-shirts For Male",
    "price": "$3.00",
    "company": "Dongguan Qiandao Industrial Co., Ltd.",
    "moq": "Min. order: 50 pieces",
    "rating": "4.8",
    "image": "https://s.alicdn.com/@sc04/kf/Aeb88996b882e4219bd5610ef7448c235G.jpg_300x300.jpg",
    "link": "https://www.alibaba.com/product-detail/2024-Brand-New-Cotton-Men-s_11000015833403.html?selectedCarrierCode=SEMI_MANAGED_STANDARD@@STANDARD"
  },
  {
    "title": "Factory Custom Wholesale New Nano Hydrophobic Stain Resistant Round Neck T Shirts for Waterproof Quick Dry",
    "price": "$11.99",
    "company": "Jiangxi Dingsheng Imp.& Exp. Co., Ltd.",
    "moq": "Min. order: 2 pieces",
    "rating": "5.0",
    "image": "https://s.alicdn.com/@sc04/kf/Hbb6dcf44e422460d8a05369a6d7da704E.jpg_300x300.jpg",
    "link": "https://www.alibaba.com/product-detail/Factory-Custom-Wholesale-New-Nano-Hydrophobic_1601210775578.html?selectedCarrierCode=SEMI_MANAGED_STANDARD@@STANDARD"
  },
  {
    "title": "180 Gsm High Quality 100% Cotton Plus Size Man's T-Shirts Custom Print Logo Blank Unisex Solid Colour T Shirt for Men",
    "price": "$3.33",
    "company": "Guangzhou Kroad Clothing Co., Ltd.",
    "moq": "Min. order: 5 pieces",
    "rating": "4.9",
    "image": "https://s.alicdn.com/@sc04/kf/Ha56be8a42f8245a796048e5ccd43e564p.jpg_300x300.jpg",
    "link": "https://www.alibaba.com/product-detail/180-Gsm-High-Quality-100-Cotton_1601113410156.html?selectedCarrierCode=SEMI_MANAGED_STANDARD@@STANDARD"
  },
  {
    "title": "250GSM soft cotton blank man's oversized heavyweight tshirt Short Sleeve Blank Streetwear T Shirt",
    "price": "$4.86",
    "company": "Yiwu Qianying Import And Export Co., Ltd.",
    "moq": "Min. order: 10 pieces",
    "rating": "4.8",
    "image": "https://s.alicdn.com/@sc04/kf/H27fbbd47564f408c84d5eaeeed5f3b24s.jpg_300x300.jpg",
    "link": "https://www.alibaba.com/product-detail/250GSM-soft-cotton-blank-man-s_1601074322097.html?selectedCarrierCode=SEMI_MANAGED_STANDARD@@STANDARD"
  },
  {
    "title": "Men's T-shirt Custom LOGO picture T-shirt Printed LOGO casual high quality blank super large 100% cotton",
    "price": "$3.80",
    "company": "Yiwu Yi Yi Clothing Co., Ltd.",
    "moq": "Min. order: 2 pieces",
    "rating": "4.8",
    "image": "https://s.alicdn.com/@sc04/kf/H3a713fe14cc14981835cb083f0d0c25bf.jpg_300x300.jpg",
    "link": "https://www.alibaba.com/product-detail/Men-s-T-shirt-Custom-LOGO_1600506041084.html?selectedCarrierCode=SEMI_MANAGED_STANDARD@@STANDARD"
  },
  {
    "title": "Enerup Custom t shirt for men men's t-shirts clothes oversized gym wear quick-dry long sleeve Tshirt",
    "price": "$6.55",
    "company": "Harvest Spf Textile(Beijing) Co., Ltd.",
    "moq": "Min. order: 3 pieces",
    "rating": "4.8",
    "image": "https://s.alicdn.com/@sc04/kf/Hffd7fde9c7f8428ab8980c93aeec3e02s.jpg_300x300.jpg",
    "link": "https://www.alibaba.com/product-detail/Enerup-Custom-t-shirt-for-men_1601177816077.html"
  },
  {
    "title": "CSXM-002 Man's high quality short sleeve running wear fitness gym wear quick dry sports shirt fashion activewear",
    "price": "$5.00",
    "company": "Dongguan Lanteng Sports Products Co., Ltd.",
    "moq": "Min. order: 1 piece",
    "rating": "4.8",
    "image": "https://s.alicdn.com/@sc04/kf/H6a8c210dd20545ae852b96b05c224790B.jpg_300x300.jpg",
    "link": "https://www.alibaba.com/product-detail/CSXM-002-Man-s-high-quality_1601210992081.html?selectedCarrierCode=SEMI_MANAGED_STANDARD@@STANDARD"
  },
  {
    "title": "Unisex 310g Heavyweight American High Street Style Trendy Brand Pure Cotton Solid Color Long Sleeved Loose Fit",
    "price": "$12.60",
    "company": "Guangzhou Chenyi Sports Products Co., Ltd.",
    "moq": "Min. order: 1 piece",
    "rating": "4.7",
    "image": "https://s.alicdn.com/@sc04/kf/H17e864366d624b91a5a493cb281e8f86G.jpg_300x300.jpg",
    "link": "https://www.alibaba.com/product-detail/Unisex-310g-Heavyweight-American-High-Street_1601270323533.html?selectedCarrierCode=SEMI_MANAGED_STANDARD@@STANDARD"
  },
  {
    "title": "Custom Order High Quality EMF Protective Man's Anti Radiation T Shirt",
    "price": "$75.00",
    "company": "Suzhou Sinkery Electronic Technology Co., Ltd.",
    "moq": "Min. order: 1 unit",
    "rating": "4.9",
    "image": "https://s.alicdn.com/@sc04/kf/H9439608ef16e4faeb58fab2a0c4cb5d4A.jpg_300x300.jpg",
    "link": "https://www.alibaba.com/product-detail/Custom-Order-High-Quality-EMF-Protective_62559124924.html"
  },
  {
    "title": "Custom Men Short Drop Sleeve Loose Fit O-Neck Cotton",
    "price": "$6.90",
    "company": "Dongguan AOGU Sportswear Co., Ltd.",
    "moq": "Min. order: 100 pieces",
    "rating": "4.8",
    "image": "https://s.alicdn.com/@sc04/kf/H866eceb50c7d42368ae787c20d8a46b3c.jpg_300x300.jpg",
    "link": "https://www.alibaba.com/product-detail/Custom-Men-Short-Drop-Sleeve-Loose_1601259772708.html"
  },
  {
    "title": "New Design 7XL high quality Custom shirt various colors birthday gift Button shirt",
    "price": "$7.50",
    "company": "Hangzhou Oneplus Industrial Co., Ltd.",
    "moq": "Min. order: 2 pieces",
    "rating": "4.6",
    "image": "https://s.alicdn.com/@sc04/kf/H579e3d5867444f99871761b2121fac27C.jpg_300x300.jpg",
    "link": "https://www.alibaba.com/product-detail/New-Design-7XL-high-quality-Custom_1600860375377.html?selectedCarrierCode=SEMI_MANAGED_STANDARD@@STANDARD"
  },
  {
    "title": "Cheap Wholesale Summer Quick Drying And Breathable Casual Long-Sleeve Two-Piece",
    "price": "$6.66",
    "company": "Fujian Shishi Chaorui Chimelong Trading Co., Ltd.",
    "moq": "Min. order: 10 pieces",
    "rating": "4.9",
    "image": "https://s.alicdn.com/@sc04/kf/H1f1b13d595dd4d80aefa7f484b888b3f2.jpg_300x300.jpg",
    "link": "https://www.alibaba.com/product-detail/Cheap-Wholesale-Summer-Quick-Drying-And_1601253546605.html?selectedCarrierCode=SEMI_MANAGED_STANDARD@@STANDARD"
  },
  {
    "title": "Customized plain white printed t shirt for men",
    "price": "$7.00",
    "company": "Guangzhou Ishang Apparel Co., Ltd.",
    "moq": "Min. order: 2 pieces",
    "rating": "5.0",
    "image": "https://s.alicdn.com/@sc04/kf/H44584dbadb8c4a518fe2c2d0e0112b66V.jpg_300x300.jpg",
    "link": "https://www.alibaba.com/product-detail/Customized-plain-white-printed-t-shirt_1601294900998.html?selectedCarrierCode=SEMI_MANAGED_STANDARD@@STANDARD"
  },
  {
    "title": "Manufacturer Custom Logo Tee Shirt 200gsm Combed Cotton Unisex Casual Short Style Embroidery Printing Blank Plain T Shirt",
    "price": "$8.88",
    "company": "Jiangxi Dani Clothing Co., Ltd.",
    "moq": "Min. order: 30 pieces",
    "rating": "4.7",
    "image": "https://s.alicdn.com/@sc04/kf/H4e07104ac6f04b85982bcfc3977ca9fa4.jpg_300x300.jpg",
    "link": "https://www.alibaba.com/product-detail/Manufacturer-Custom-Logo-Tee-Shirt-200gsm_1601214160130.html?selectedCarrierCode=SEMI_MANAGED_STANDARD@@STANDARD"
  },
  {
    "title": "Men's T-shirt Custom LOGO picture T-shirt Printed LOGO casual high quality blank super large 100% cotton",
    "price": "$3.65",
    "company": "Hainan Yinlin Trading Co., Ltd.",
    "moq": "Min. order: 20 pieces",
    "rating": "4.4",
    "image": "https://s.alicdn.com/@sc04/kf/H0a26d2bc745b40a8a4bc1da09bcf58359.jpg_300x300.jpg",
    "link": "https://www.alibaba.com/product-detail/Men-s-T-shirt-Custom-LOGO_1601221659108.html?selectedCarrierCode=SEMI_MANAGED_STANDARD@@STANDARD"
  },
  {
    "title": "180g polyester fiber spandex T-shirt European size long-sleeved shirt sports quick-drying gym clothes custom logo tshirts",
    "price": "$5.96",
    "company": "Guangzhou Sebanda Trading Co., Ltd.",
    "moq": "Min. order: 10 pieces",
    "rating": "4.9",
    "image": "https://s.alicdn.com/@sc04/kf/Hbfcb8854f59f4a9489f5366c1ea89228R.jpg_300x300.jpg",
    "link": "https://www.alibaba.com/product-detail/180g-polyester-fiber-spandex-T-shirt_1600304762873.html?selectedCarrierCode=SEMI_MANAGED_STANDARD@@STANDARD"
  },
  {
    "title": "High quality in stock heavyweight oversized cotton white long sleeve t shirts",
    "price": "$19.30",
    "company": "Guangzhou Ruifeng Import And Export Trade Co., Ltd.",
    "moq": "Min. order: 2 pieces",
    "rating": "4.1",
    "image": "https://s.alicdn.com/@sc04/kf/H4908d0f2ce6849899f1cd91d5d92a397f.jpg_300x300.jpg",
    "link": "https://www.alibaba.com/product-detail/High-quality-in-stock-heavyweight-oversized_1601014172324.html?selectedCarrierCode=SEMI_MANAGED_STANDARD@@STANDARD"
  },
  {
    "title": "High Quality Quick Dry Man's T-Shirt Comfortable Oversized Disrupted Style Solid Pattern Customizable Blank Design",
    "price": "$7.82",
    "company": "Xiamen Starsky Industry Co., Ltd.",
    "moq": "Min. order: 5 pieces",
    "rating": "4.7",
    "image": "https://s.alicdn.com/@sc04/kf/H07852aabde4d4ec19fd3e2fe7722de8e9.jpg_300x300.jpg",
    "link": "https://www.alibaba.com/product-detail/High-Quality-Quick-Dry-Man-s_1601348081336.html?selectedCarrierCode=SEMI_MANAGED_STANDARD@@STANDARD"
  },
  {
    "title": "Men's Comfort Ribbed Henry Button Shirt Muscle Cotton Short Sleeve Casual Breathable",
    "price": "$5.87",
    "company": "Guangzhou Mingying Trading Co., Ltd.",
    "moq": "Min. order: 150 pieces",
    "rating": "4.1",
    "image": "https://s.alicdn.com/@sc04/kf/H7bc9ae00110c4e65aa2f092dd4d074f3r.jpg_300x300.jpg",
    "link": "https://www.alibaba.com/product-detail/Men-s-Comfort-Ribbed-Henry-Button_1601214014049.html?selectedCarrierCode=SEMI_MANAGED_STANDARD@@STANDARD"
  },
  {
    "title": "Men Clothing Summer Custom Daily Fit Grey Short Sleeves Tee Gym Oversized T Shirt",
    "price": "$10.35",
    "company": "Dongguan Betteractive Fashion Co., Ltd.",
    "moq": "Min. order: 5 pieces",
    "rating": "4.8",
    "image": "https://s.alicdn.com/@sc04/kf/H852efa4c6d6d4b3d8ab652e9d1ae0f7cc.jpg_300x300.jpg",
    "link": "https://www.alibaba.com/product-detail/Men-Clothing-Summer-Custom-Daily-Fit_1600818471368.html?selectedCarrierCode=SEMI_MANAGED_STANDARD@@STANDARD"
  }
]